fortilib-1.0.15.dist-info/METADATA
fortilib-1.0.15.dist-info/WHEEL
fortilib-1.0.15.dist-info/entry_points.txt
fortilib-1.0.15.dist-info/licenses/LICENSE
fortilib/__init__.py
fortilib/address.py
fortilib/addressgroup.py
fortilib/base.py
fortilib/exceptions.py
fortilib/firewall.py
fortilib/fortigateapi.py
fortilib/fortilib.iml
fortilib/fortiproxy.py
fortilib/interface.py
fortilib/ippool.py
fortilib/mixins/__init__.py
fortilib/mixins/group.py
fortilib/mixins/interface.py
fortilib/phase1interface.py
fortilib/phase2interface.py
fortilib/policy.py
fortilib/proxyaddress.py
fortilib/proxyaddressgroup.py
fortilib/proxypolicy.py
fortilib/routes.py
fortilib/service.py
fortilib/servicegroup.py
fortilib/vip.py
fortilib/vipgroup.py
fortilib-1.0.15.dist-info/RECORD
