Metadata-Version: 2.1
Name: fortilib
Version: 1.0.15
Summary: fortilib - a Python Library to interact with Fortigate Firewalls
Keywords: firewall,fortinet,fortigate
Author-Email: Daniel Zinke <Daniel.Zinke@telekom.de>, =?utf-8?q?Benjamin_B=C3=B6hm?= <Benjamin.Boehm@telekom.de>, Philipp Funk <Philipp.Funk@telekom.de>, =?utf-8?q?Andr=C3=A9_Ellguth?= <Andre.Ellguth@telekom.de>, Martin Neubert <Martin.Neubert@telekom.de>
License: GPL-3.0-only
Project-URL: Changelog, https://github.com/telekom-mms/fortilib/blob/master/CHANGELOG.md
Project-URL: homepage, https://github.com/telekom-mms/fortilib
Project-URL: repository, https://github.com/telekom-mms/fortilib
Project-URL: documentation, https://github.com/telekom-mms/fortilib
Requires-Python: <4.0,>=3.11
Requires-Dist: httpx<0.29.0,>=0.28.1
